calc/__init__.py
calc/__main__.py
calc/calculator.py
shsamariddin-1.0.7.dist-info/LICENSE
shsamariddin-1.0.7.dist-info/METADATA
shsamariddin-1.0.7.dist-info/WHEEL
shsamariddin-1.0.7.dist-info/entry_points.txt
shsamariddin-1.0.7.dist-info/top_level.txt
shsamariddin-1.0.7.dist-info/RECORD
