Metadata-Version: 2.1
Name: shsamariddin
Version: 1.0.7
Summary: It squares the number
Home-page: https://github.com/shsamariddin
Author: Sharipov Samariddin
Author-email: samariddin-sharipov-99@mail.ru
License: MIT
Platform: UNKNOWN
Classifier: License :: OSI Approved :: MIT License
Classifier: Programming Language :: Python :: 3.6
Classifier: Programming Language :: Python :: 3.7
Classifier: Programming Language :: Python :: 3.8
License-File: LICENSE
Requires-Dist: matplotlib
Requires-Dist: typing
Requires-Dist: numpy
